alembic_tools/__init__.py
alembic_tools/migrator.py
alembic_tools/script.py.mako
alembic_tools-0.3.0.dist-info/LICENSE
alembic_tools-0.3.0.dist-info/METADATA
alembic_tools-0.3.0.dist-info/WHEEL
alembic_tools-0.3.0.dist-info/RECORD
