Metadata-Version: 2.1
Name: alembic-tools
Version: 0.3.0
Summary: Tools anhanced alembic model
Home-page: https://github.com/smairon/alembic-tools
Author: Smairon
Author-email: man@smairon.ru
Requires-Python: >=3.11,<4.0
Classifier: Programming Language :: Python :: 3
Classifier: Programming Language :: Python :: 3.11
Classifier: Programming Language :: Python :: 3.12
Requires-Dist: alembic (>=1.16.1,<2.0.0)
Requires-Dist: asyncpg (>=0.30,<0.31)
Requires-Dist: greenlet (>=3.2.3,<4.0.0)
Project-URL: Repository, https://github.com/smairon/alembic-tools
